{"RepositoryId":261166328,"Url":"https://github.com/fireactjs/saas","Name":"saas","Description":"A fully functional React web application for SaaS projects. It's built with React, Firebase and Stripe.","License":"","Topics":null,"Stars":441,"Watchers":441,"Forks":165,"Size":1360,"Archived":false,"Forked":false,"CreatedAt":"2020-05-04T12:14:34Z","PushedAt":"2024-01-07T11:01:02Z","NumContributors":2,"NumIssues":40,"NumOpenIssues":5,"NumClosedIssues":35,"NumCommits":258,"FirstCommitAt":"2020-11-28T05:19:41Z","FirstHumanCommitAt":"2020-11-28T05:19:41Z","LastCommitAt":"2024-05-11T01:15:23Z","LastHumanCommitAt":"2024-05-11T01:15:23Z","ActiveDays":1260,"ActiveHumanDays":1260,"Complexity":{"Files":[{"Extension":".DS_Store","Name":".DS_Store","Path":"data/repositories/261166328/.DS_Store","Language":".DS_Store","Category":"Other","LOC":0,"NumCharacters":0},{"Extension":".gitignore","Name":".gitignore","Path":"data/repositories/261166328/.gitignore","Language":".gitignore","Category":"Other","LOC":0,"NumCharacters":0},{"Extension":".gitmodules","Name":".gitmodules","Path":"data/repositories/261166328/.gitmodules","Language":".gitmodules","Category":"Other","LOC":0,"NumCharacters":0},{"Extension":".md","Name":"README.md","Path":"data/repositories/261166328/README.md","Language":"Markdown","Category":"Documentation","LOC":0,"NumCharacters":0},{"Extension":".json","Name":"babel.config.cjs.json","Path":"data/repositories/261166328/babel.config.cjs.json","Language":"JSON","Category":"Data","LOC":0,"NumCharacters":0},{"Extension":".json","Name":"babel.config.esm.json","Path":"data/repositories/261166328/babel.config.esm.json","Language":"JSON","Category":"Data","LOC":0,"NumCharacters":0},{"Extension":".js","Name":"AddUser.js","Path":"data/repositories/261166328/dist/cjs/components/AddUser.js","Language":"JavaScript","Category":"Source Code","LOC":161,"NumCharacters":5759},{"Extension":".js","Name":"BillingDetails.js","Path":"data/repositories/261166328/dist/cjs/components/BillingDetails.js","Language":"JavaScript","Category":"Source Code","LOC":193,"NumCharacters":7412},{"Extension":".js","Name":"CancelSubscription.js","Path":"data/repositories/261166328/dist/cjs/components/CancelSubscription.js","Language":"JavaScript","Category":"Source Code","LOC":100,"NumCharacters":4388},{"Extension":".js","Name":"ChangePlan.js","Path":"data/repositories/261166328/dist/cjs/components/ChangePlan.js","Language":"JavaScript","Category":"Source Code","LOC":175,"NumCharacters":8295},{"Extension":".js","Name":"CreateSubscription.js","Path":"data/repositories/261166328/dist/cjs/components/CreateSubscription.js","Language":"JavaScript","Category":"Source Code","LOC":151,"NumCharacters":6138},{"Extension":".js","Name":"ListInvoices.js","Path":"data/repositories/261166328/dist/cjs/components/ListInvoices.js","Language":"JavaScript","Category":"Source Code","LOC":188,"NumCharacters":7070},{"Extension":".js","Name":"ListSubscriptions.js","Path":"data/repositories/261166328/dist/cjs/components/ListSubscriptions.js","Language":"JavaScript","Category":"Source Code","LOC":181,"NumCharacters":8208},{"Extension":".js","Name":"ListUsers.js","Path":"data/repositories/261166328/dist/cjs/components/ListUsers.js","Language":"JavaScript","Category":"Source Code","LOC":235,"NumCharacters":7822},{"Extension":".js","Name":"ManagePaymentMethods.js","Path":"data/repositories/261166328/dist/cjs/components/ManagePaymentMethods.js","Language":"JavaScript","Category":"Source Code","LOC":251,"NumCharacters":11024},{"Extension":".js","Name":"PaginationTable.js","Path":"data/repositories/261166328/dist/cjs/components/PaginationTable.js","Language":"JavaScript","Category":"Source Code","LOC":40,"NumCharacters":1571},{"Extension":".js","Name":"PaymentMethodForm.js","Path":"data/repositories/261166328/dist/cjs/components/PaymentMethodForm.js","Language":"JavaScript","Category":"Source Code","LOC":140,"NumCharacters":4280},{"Extension":".js","Name":"PermissionRouter.js","Path":"data/repositories/261166328/dist/cjs/components/PermissionRouter.js","Language":"JavaScript","Category":"Source Code","LOC":30,"NumCharacters":1926},{"Extension":".js","Name":"PricingPlans.js","Path":"data/repositories/261166328/dist/cjs/components/PricingPlans.js","Language":"JavaScript","Category":"Source Code","LOC":89,"NumCharacters":3617},{"Extension":".js","Name":"Settings.js","Path":"data/repositories/261166328/dist/cjs/components/Settings.js","Language":"JavaScript","Category":"Source Code","LOC":110,"NumCharacters":5687},{"Extension":".js","Name":"SubscriptionContext.js","Path":"data/repositories/261166328/dist/cjs/components/SubscriptionContext.js","Language":"JavaScript","Category":"Source Code","LOC":72,"NumCharacters":3311},{"Extension":".js","Name":"SubscriptionMenu.js","Path":"data/repositories/261166328/dist/cjs/components/SubscriptionMenu.js","Language":"JavaScript","Category":"Source Code","LOC":97,"NumCharacters":5463},{"Extension":".js","Name":"UpdateBillingDetails.js","Path":"data/repositories/261166328/dist/cjs/components/UpdateBillingDetails.js","Language":"JavaScript","Category":"Source Code","LOC":111,"NumCharacters":4895},{"Extension":".js","Name":"UpdateUser.js","Path":"data/repositories/261166328/dist/cjs/components/UpdateUser.js","Language":"JavaScript","Category":"Source Code","LOC":204,"NumCharacters":8558},{"Extension":".json","Name":"currencies.json","Path":"data/repositories/261166328/dist/cjs/components/currencies.json","Language":"JSON","Category":"Data","LOC":0,"NumCharacters":0},{"Extension":".js","Name":"utilities.js","Path":"data/repositories/261166328/dist/cjs/components/utilities.js","Language":"JavaScript","Category":"Source Code","LOC":20,"NumCharacters":493},{"Extension":".js","Name":"index.js","Path":"data/repositories/261166328/dist/cjs/index.js","Language":"JavaScript","Category":"Source Code","LOC":144,"NumCharacters":3947},{"Extension":".json","Name":"pathnames.json","Path":"data/repositories/261166328/dist/cjs/pathnames.json","Language":"JSON","Category":"Data","LOC":0,"NumCharacters":0},{"Extension":".js","Name":"AddUser.js","Path":"data/repositories/261166328/dist/esm/components/AddUser.js","Language":"JavaScript","Category":"Source Code","LOC":152,"NumCharacters":4296},{"Extension":".js","Name":"BillingDetails.js","Path":"data/repositories/261166328/dist/esm/components/BillingDetails.js","Language":"JavaScript","Category":"Source Code","LOC":184,"NumCharacters":5928},{"Extension":".js","Name":"CancelSubscription.js","Path":"data/repositories/261166328/dist/esm/components/CancelSubscription.js","Language":"JavaScript","Category":"Source Code","LOC":91,"NumCharacters":3010},{"Extension":".js","Name":"ChangePlan.js","Path":"data/repositories/261166328/dist/esm/components/ChangePlan.js","Language":"JavaScript","Category":"Source Code","LOC":166,"NumCharacters":6764},{"Extension":".js","Name":"CreateSubscription.js","Path":"data/repositories/261166328/dist/esm/components/CreateSubscription.js","Language":"JavaScript","Category":"Source Code","LOC":142,"NumCharacters":4649},{"Extension":".js","Name":"ListInvoices.js","Path":"data/repositories/261166328/dist/esm/components/ListInvoices.js","Language":"JavaScript","Category":"Source Code","LOC":178,"NumCharacters":5364},{"Extension":".js","Name":"ListSubscriptions.js","Path":"data/repositories/261166328/dist/esm/components/ListSubscriptions.js","Language":"JavaScript","Category":"Source Code","LOC":172,"NumCharacters":6475},{"Extension":".js","Name":"ListUsers.js","Path":"data/repositories/261166328/dist/esm/components/ListUsers.js","Language":"JavaScript","Category":"Source Code","LOC":226,"NumCharacters":6237},{"Extension":".js","Name":"ManagePaymentMethods.js","Path":"data/repositories/261166328/dist/esm/components/ManagePaymentMethods.js","Language":"JavaScript","Category":"Source Code","LOC":242,"NumCharacters":9195},{"Extension":".js","Name":"PaginationTable.js","Path":"data/repositories/261166328/dist/esm/components/PaginationTable.js","Language":"JavaScript","Category":"Source Code","LOC":33,"NumCharacters":1179},{"Extension":".js","Name":"PaymentMethodForm.js","Path":"data/repositories/261166328/dist/esm/components/PaymentMethodForm.js","Language":"JavaScript","Category":"Source Code","LOC":131,"NumCharacters":3007},{"Extension":".js","Name":"PermissionRouter.js","Path":"data/repositories/261166328/dist/esm/components/PermissionRouter.js","Language":"JavaScript","Category":"Source Code","LOC":20,"NumCharacters":720},{"Extension":".js","Name":"PricingPlans.js","Path":"data/repositories/261166328/dist/esm/components/PricingPlans.js","Language":"JavaScript","Category":"Source Code","LOC":78,"NumCharacters":2229},{"Extension":".js","Name":"Settings.js","Path":"data/repositories/261166328/dist/esm/components/Settings.js","Language":"JavaScript","Category":"Source Code","LOC":102,"NumCharacters":4375},{"Extension":".js","Name":"SubscriptionContext.js","Path":"data/repositories/261166328/dist/esm/components/SubscriptionContext.js","Language":"JavaScript","Category":"Source Code","LOC":63,"NumCharacters":1949},{"Extension":".js","Name":"SubscriptionMenu.js","Path":"data/repositories/261166328/dist/esm/components/SubscriptionMenu.js","Language":"JavaScript","Category":"Source Code","LOC":86,"NumCharacters":3617},{"Extension":".js","Name":"UpdateBillingDetails.js","Path":"data/repositories/261166328/dist/esm/components/UpdateBillingDetails.js","Language":"JavaScript","Category":"Source Code","LOC":102,"NumCharacters":3387},{"Extension":".js","Name":"UpdateUser.js","Path":"data/repositories/261166328/dist/esm/components/UpdateUser.js","Language":"JavaScript","Category":"Source Code","LOC":195,"NumCharacters":6893},{"Extension":".json","Name":"currencies.json","Path":"data/repositories/261166328/dist/esm/components/currencies.json","Language":"JSON","Category":"Data","LOC":0,"NumCharacters":0},{"Extension":".js","Name":"utilities.js","Path":"data/repositories/261166328/dist/esm/components/utilities.js","Language":"JavaScript","Category":"Source Code","LOC":14,"NumCharacters":352},{"Extension":".js","Name":"index.js","Path":"data/repositories/261166328/dist/esm/index.js","Language":"JavaScript","Category":"Source Code","LOC":20,"NumCharacters":1504},{"Extension":".json","Name":"pathnames.json","Path":"data/repositories/261166328/dist/esm/pathnames.json","Language":"JSON","Category":"Data","LOC":0,"NumCharacters":0},{"Extension":".json","Name":"firestore.indexes.json","Path":"data/repositories/261166328/firestore.indexes.json","Language":"JSON","Category":"Data","LOC":0,"NumCharacters":0},{"Extension":".rules","Name":"firestore.rules","Path":"data/repositories/261166328/firestore.rules","Language":".rules","Category":"Other","LOC":0,"NumCharacters":0},{"Extension":".gitignore","Name":".gitignore","Path":"data/repositories/261166328/functions/.gitignore","Language":".gitignore","Category":"Other","LOC":0,"NumCharacters":0},{"Extension":".js","Name":"index.js","Path":"data/repositories/261166328/functions/index.js","Language":"JavaScript","Category":"Source Code","LOC":12,"NumCharacters":518},{"Extension":".js","Name":"index.js","Path":"data/repositories/261166328/functions/lib/index.js","Language":"JavaScript","Category":"Source Code","LOC":664,"NumCharacters":19130},{"Extension":".json","Name":"package-lock.json","Path":"data/repositories/261166328/functions/package-lock.json","Language":"JSON","Category":"Data","LOC":0,"NumCharacters":0},{"Extension":".json","Name":"package.json","Path":"data/repositories/261166328/functions/package.json","Language":"JSON","Category":"Data","LOC":0,"NumCharacters":0},{"Extension":".json","Name":"package-lock.json","Path":"data/repositories/261166328/package-lock.json","Language":"JSON","Category":"Data","LOC":0,"NumCharacters":0},{"Extension":".json","Name":"package.json","Path":"data/repositories/261166328/package.json","Language":"JSON","Category":"Data","LOC":0,"NumCharacters":0},{"Extension":".ico","Name":"favicon.ico","Path":"data/repositories/261166328/public/favicon.ico","Language":".ico","Category":"Asset","LOC":0,"NumCharacters":0},{"Extension":".html","Name":"index.html","Path":"data/repositories/261166328/public/index.html","Language":"HTML","Category":"Source Code","LOC":40,"NumCharacters":1506},{"Extension":".png","Name":"logo192.png","Path":"data/repositories/261166328/public/logo192.png","Language":".png","Category":"Asset","LOC":0,"NumCharacters":0},{"Extension":".png","Name":"logo512.png","Path":"data/repositories/261166328/public/logo512.png","Language":".png","Category":"Asset","LOC":0,"NumCharacters":0},{"Extension":".json","Name":"manifest.json","Path":"data/repositories/261166328/public/manifest.json","Language":"JSON","Category":"Data","LOC":0,"NumCharacters":0},{"Extension":".txt","Name":"robots.txt","Path":"data/repositories/261166328/public/robots.txt","Language":"Plain Text","Category":"Data","LOC":0,"NumCharacters":0},{"Extension":".css","Name":"App.css","Path":"data/repositories/261166328/src/App.css","Language":"CSS","Category":"Source Code","LOC":33,"NumCharacters":478},{"Extension":".js","Name":"App.js","Path":"data/repositories/261166328/src/App.js","Language":"JavaScript","Category":"Source Code","LOC":115,"NumCharacters":4226},{"Extension":".json","Name":"authMethods.json","Path":"data/repositories/261166328/src/authMethods.json","Language":"JSON","Category":"Data","LOC":0,"NumCharacters":0},{"Extension":".css","Name":"index.css","Path":"data/repositories/261166328/src/index.css","Language":"CSS","Category":"Source Code","LOC":12,"NumCharacters":331},{"Extension":".js","Name":"index.js","Path":"data/repositories/261166328/src/index.js","Language":"JavaScript","Category":"Source Code","LOC":15,"NumCharacters":510},{"Extension":".js","Name":"AddUser.js","Path":"data/repositories/261166328/src/lib/components/AddUser.js","Language":"JavaScript","Category":"Source Code","LOC":117,"NumCharacters":3376},{"Extension":".js","Name":"BillingDetails.js","Path":"data/repositories/261166328/src/lib/components/BillingDetails.js","Language":"JavaScript","Category":"Source Code","LOC":122,"NumCharacters":3187},{"Extension":".js","Name":"CancelSubscription.js","Path":"data/repositories/261166328/src/lib/components/CancelSubscription.js","Language":"JavaScript","Category":"Source Code","LOC":65,"NumCharacters":2291},{"Extension":".js","Name":"ChangePlan.js","Path":"data/repositories/261166328/src/lib/components/ChangePlan.js","Language":"JavaScript","Category":"Source Code","LOC":163,"NumCharacters":4479},{"Extension":".js","Name":"CreateSubscription.js","Path":"data/repositories/261166328/src/lib/components/CreateSubscription.js","Language":"JavaScript","Category":"Source Code","LOC":153,"NumCharacters":3877},{"Extension":".js","Name":"ListInvoices.js","Path":"data/repositories/261166328/src/lib/components/ListInvoices.js","Language":"JavaScript","Category":"Source Code","LOC":124,"NumCharacters":4397},{"Extension":".js","Name":"ListSubscriptions.js","Path":"data/repositories/261166328/src/lib/components/ListSubscriptions.js","Language":"JavaScript","Category":"Source Code","LOC":154,"NumCharacters":5185},{"Extension":".js","Name":"ListUsers.js","Path":"data/repositories/261166328/src/lib/components/ListUsers.js","Language":"JavaScript","Category":"Source Code","LOC":169,"NumCharacters":5202},{"Extension":".js","Name":"ManagePaymentMethods.js","Path":"data/repositories/261166328/src/lib/components/ManagePaymentMethods.js","Language":"JavaScript","Category":"Source Code","LOC":211,"NumCharacters":6362},{"Extension":".js","Name":"PaginationTable.js","Path":"data/repositories/261166328/src/lib/components/PaginationTable.js","Language":"JavaScript","Category":"Source Code","LOC":37,"NumCharacters":842},{"Extension":".js","Name":"PaymentMethodForm.js","Path":"data/repositories/261166328/src/lib/components/PaymentMethodForm.js","Language":"JavaScript","Category":"Source Code","LOC":94,"NumCharacters":2524},{"Extension":".js","Name":"PermissionRouter.js","Path":"data/repositories/261166328/src/lib/components/PermissionRouter.js","Language":"JavaScript","Category":"Source Code","LOC":19,"NumCharacters":593},{"Extension":".js","Name":"PricingPlans.js","Path":"data/repositories/261166328/src/lib/components/PricingPlans.js","Language":"JavaScript","Category":"Source Code","LOC":79,"NumCharacters":1739},{"Extension":".js","Name":"Settings.js","Path":"data/repositories/261166328/src/lib/components/Settings.js","Language":"JavaScript","Category":"Source Code","LOC":71,"NumCharacters":2315},{"Extension":".js","Name":"SubscriptionContext.js","Path":"data/repositories/261166328/src/lib/components/SubscriptionContext.js","Language":"JavaScript","Category":"Source Code","LOC":58,"NumCharacters":1527},{"Extension":".js","Name":"SubscriptionMenu.js","Path":"data/repositories/261166328/src/lib/components/SubscriptionMenu.js","Language":"JavaScript","Category":"Source Code","LOC":64,"NumCharacters":2629},{"Extension":".js","Name":"UpdateBillingDetails.js","Path":"data/repositories/261166328/src/lib/components/UpdateBillingDetails.js","Language":"JavaScript","Category":"Source Code","LOC":86,"NumCharacters":2619},{"Extension":".js","Name":"UpdateUser.js","Path":"data/repositories/261166328/src/lib/components/UpdateUser.js","Language":"JavaScript","Category":"Source Code","LOC":155,"NumCharacters":4240},{"Extension":".json","Name":"currencies.json","Path":"data/repositories/261166328/src/lib/components/currencies.json","Language":"JSON","Category":"Data","LOC":0,"NumCharacters":0},{"Extension":".js","Name":"utilities.js","Path":"data/repositories/261166328/src/lib/components/utilities.js","Language":"JavaScript","Category":"Source Code","LOC":14,"NumCharacters":339},{"Extension":".js","Name":"index.js","Path":"data/repositories/261166328/src/lib/index.js","Language":"JavaScript","Category":"Source Code","LOC":41,"NumCharacters":1483},{"Extension":".json","Name":"pathnames.json","Path":"data/repositories/261166328/src/lib/pathnames.json","Language":"JSON","Category":"Data","LOC":0,"NumCharacters":0},{"Extension":".svg","Name":"logo.svg","Path":"data/repositories/261166328/src/logo.svg","Language":".svg","Category":"Asset","LOC":0,"NumCharacters":0},{"Extension":".js","Name":"reportWebVitals.js","Path":"data/repositories/261166328/src/reportWebVitals.js","Language":"JavaScript","Category":"Source Code","LOC":12,"NumCharacters":307}]},"UsedPlatforms":{"firebase":true},"UsedFrameworks":{"firebase":true},"Functions":[{"Name":"","Platform":"firebase","Framework":"firebase","InvocationType":"http","Location":"region","TimeoutSeconds":-1,"SourceFilePath":"data/repositories/261166328/functions/index.js","SourceFileLine":-1},{"Name":"","Platform":"firebase","Framework":"firebase","InvocationType":"http","Location":"region","TimeoutSeconds":-1,"SourceFilePath":"data/repositories/261166328/functions/index.js","SourceFileLine":-1},{"Name":"","Platform":"firebase","Framework":"firebase","InvocationType":"http","Location":"region","TimeoutSeconds":-1,"SourceFilePath":"data/repositories/261166328/functions/lib/index.js","SourceFileLine":-1},{"Name":"","Platform":"firebase","Framework":"firebase","InvocationType":"http","Location":"region","TimeoutSeconds":-1,"SourceFilePath":"data/repositories/261166328/functions/lib/index.js","SourceFileLine":-1}],"NumFunctions":4,"Packages":[{"RootPath":"data/repositories/261166328/functions","Name":"@fireactjs/saas-cloud-functions","Description":"Cloud Functions for Firebase","Dependencies":["stripe","firebase-admin","firebase-functions","form-data","mailgun.js"],"DevDependencies":["firebase-functions-test"],"FaaSRuntimeDependencies":["firebase-functions"],"PublishedToNPM":false,"NumPackages":1,"NumFilesByExtension":null,"LinesOfTextByExtension":null,"NumFaaSHandlers":0,"NumFaaSRuntimeDependencies":1},{"RootPath":"data/repositories/261166328","Name":"@fireactjs/saas","Description":"fireactjs-saas is a package for building SaaS with React and Firebase","Dependencies":["react-country-state-fields","@babel/polyfill","@fireactjs/core","@stripe/react-stripe-js","@stripe/stripe-js"],"DevDependencies":["@babel/cli","@babel/core","@babel/preset-env","@testing-library/jest-dom","@testing-library/react","@testing-library/user-event"],"FaaSRuntimeDependencies":[],"PublishedToNPM":false,"NumPackages":2,"NumFilesByExtension":null,"LinesOfTextByExtension":null,"NumFaaSHandlers":0,"NumFaaSRuntimeDependencies":0}],"NumPackages":2,"NumPublishedToNPM":0,"Dependencies":["stripe","firebase-admin","firebase-functions","form-data","mailgun.js","react-country-state-fields","@babel/polyfill","@fireactjs/core","@stripe/react-stripe-js","@stripe/stripe-js"],"DevDependencies":["firebase-functions-test","@babel/cli","@babel/core","@babel/preset-env","@testing-library/jest-dom","@testing-library/react","@testing-library/user-event"],"FaaSRuntimeDependencies":["firebase-functions"],"NumFaaSRuntimeDependencies":1,"NumFaaSHandlers":0}