{"RepositoryId":331450643,"Url":"https://github.com/jackbow/lil-hash","Name":"lil-hash","Description":"A simple shareable URL shortener hosted on cloudflare workers","License":"MIT License","Topics":["cloudflare-workers","svelte","sveltekit","tailwindcss"],"Stars":16,"Watchers":16,"Forks":2,"Size":420,"Archived":false,"Forked":false,"CreatedAt":"2021-01-20T22:35:11Z","PushedAt":"2023-02-08T04:59:29Z","NumContributors":-1,"NumIssues":-2,"NumOpenIssues":-1,"NumClosedIssues":-1,"NumCommits":86,"FirstCommitAt":"2021-01-20T22:35:13Z","FirstHumanCommitAt":"2021-01-20T22:35:13Z","LastCommitAt":"2023-02-08T04:55:21Z","LastHumanCommitAt":"2023-02-08T04:55:21Z","ActiveDays":748,"ActiveHumanDays":748,"Complexity":{"Files":[{"Extension":".DS_Store","Name":".DS_Store","Path":"data/repositories/331450643/.DS_Store","Language":".DS_Store","Category":"Other","LOC":0,"NumCharacters":0},{"Extension":".cjs","Name":".eslintrc.cjs","Path":"data/repositories/331450643/.eslintrc.cjs","Language":"JavaScript","Category":"Source Code","LOC":15,"NumCharacters":263},{"Extension":".gitignore","Name":".gitignore","Path":"data/repositories/331450643/.gitignore","Language":".gitignore","Category":"Other","LOC":0,"NumCharacters":0},{"Extension":".gitignore","Name":".gitignore","Path":"data/repositories/331450643/.husky/.gitignore","Language":".gitignore","Category":"Other","LOC":0,"NumCharacters":0},{"Extension":"","Name":"pre-commit","Path":"data/repositories/331450643/.husky/pre-commit","Language":"","Category":"Other","LOC":0,"NumCharacters":0},{"Extension":".prettierignore","Name":".prettierignore","Path":"data/repositories/331450643/.prettierignore","Language":".prettierignore","Category":"Other","LOC":0,"NumCharacters":0},{"Extension":".prettierrc","Name":".prettierrc","Path":"data/repositories/331450643/.prettierrc","Language":".prettierrc","Category":"Other","LOC":0,"NumCharacters":0},{"Extension":"","Name":"LICENSE","Path":"data/repositories/331450643/LICENSE","Language":"","Category":"Other","LOC":0,"NumCharacters":0},{"Extension":".md","Name":"README.md","Path":"data/repositories/331450643/README.md","Language":"Markdown","Category":"Documentation","LOC":0,"NumCharacters":0},{"Extension":".json","Name":"jsconfig.json","Path":"data/repositories/331450643/jsconfig.json","Language":"JSON","Category":"Data","LOC":0,"NumCharacters":0},{"Extension":".png","Name":"logo.png","Path":"data/repositories/331450643/logo.png","Language":".png","Category":"Asset","LOC":0,"NumCharacters":0},{"Extension":".psd","Name":"logo.psd","Path":"data/repositories/331450643/logo.psd","Language":".psd","Category":"Other","LOC":0,"NumCharacters":0},{"Extension":".json","Name":"package-lock.json","Path":"data/repositories/331450643/package-lock.json","Language":"JSON","Category":"Data","LOC":0,"NumCharacters":0},{"Extension":".json","Name":"package.json","Path":"data/repositories/331450643/package.json","Language":"JSON","Category":"Data","LOC":0,"NumCharacters":0},{"Extension":".cjs","Name":"postcss.config.cjs","Path":"data/repositories/331450643/postcss.config.cjs","Language":"JavaScript","Category":"Source Code","LOC":18,"NumCharacters":430},{"Extension":".css","Name":"app.css","Path":"data/repositories/331450643/src/app.css","Language":"CSS","Category":"Source Code","LOC":21,"NumCharacters":491},{"Extension":".html","Name":"app.html","Path":"data/repositories/331450643/src/app.html","Language":"HTML","Category":"Source Code","LOC":21,"NumCharacters":818},{"Extension":".ts","Name":"global.d.ts","Path":"data/repositories/331450643/src/global.d.ts","Language":"TypeScript","Category":"Source Code","LOC":1,"NumCharacters":39},{"Extension":".svelte","Name":"Footer.svelte","Path":"data/repositories/331450643/src/lib/components/Footer.svelte","Language":"Svelte","Category":"Source Code","LOC":60,"NumCharacters":1525},{"Extension":".css","Name":"averia-serif.css","Path":"data/repositories/331450643/src/lib/fonts/averia-serif.css","Language":"CSS","Category":"Source Code","LOC":8,"NumCharacters":46953},{"Extension":".js","Name":"adjectives.js","Path":"data/repositories/331450643/src/lib/utility/random-phrase/lists/adjectives.js","Language":"JavaScript","Category":"Source Code","LOC":229,"NumCharacters":2362},{"Extension":".js","Name":"adverbs.js","Path":"data/repositories/331450643/src/lib/utility/random-phrase/lists/adverbs.js","Language":"JavaScript","Category":"Source Code","LOC":402,"NumCharacters":4655},{"Extension":".js","Name":"nouns.js","Path":"data/repositories/331450643/src/lib/utility/random-phrase/lists/nouns.js","Language":"JavaScript","Category":"Source Code","LOC":1425,"NumCharacters":12804},{"Extension":".js","Name":"simple-words.js","Path":"data/repositories/331450643/src/lib/utility/random-phrase/lists/simple-words.js","Language":"JavaScript","Category":"Source Code","LOC":1001,"NumCharacters":8054},{"Extension":".js","Name":"random-phrase.js","Path":"data/repositories/331450643/src/lib/utility/random-phrase/random-phrase.js","Language":"JavaScript","Category":"Source Code","LOC":21,"NumCharacters":698},{"Extension":".js","Name":"valid-url.js","Path":"data/repositories/331450643/src/lib/utility/valid-url.js","Language":"JavaScript","Category":"Source Code","LOC":10,"NumCharacters":164},{"Extension":".svelte","Name":"404.svelte","Path":"data/repositories/331450643/src/routes/404.svelte","Language":"Svelte","Category":"Source Code","LOC":1,"NumCharacters":80},{"Extension":".js","Name":"[redirectKey].js","Path":"data/repositories/331450643/src/routes/[redirectKey].js","Language":"JavaScript","Category":"Source Code","LOC":11,"NumCharacters":199},{"Extension":".svelte","Name":"__layout.svelte","Path":"data/repositories/331450643/src/routes/__layout.svelte","Language":"Svelte","Category":"Source Code","LOC":7,"NumCharacters":96},{"Extension":".js","Name":"hash.js","Path":"data/repositories/331450643/src/routes/hash.js","Language":"JavaScript","Category":"Source Code","LOC":27,"NumCharacters":880},{"Extension":".svelte","Name":"hashed.svelte","Path":"data/repositories/331450643/src/routes/hashed.svelte","Language":"Svelte","Category":"Source Code","LOC":44,"NumCharacters":978},{"Extension":".svelte","Name":"index.svelte","Path":"data/repositories/331450643/src/routes/index.svelte","Language":"Svelte","Category":"Source Code","LOC":50,"NumCharacters":1212},{"Extension":".png","Name":"apple-touch-icon.png","Path":"data/repositories/331450643/static/apple-touch-icon.png","Language":".png","Category":"Asset","LOC":0,"NumCharacters":0},{"Extension":".png","Name":"favicon-16x16.png","Path":"data/repositories/331450643/static/favicon-16x16.png","Language":".png","Category":"Asset","LOC":0,"NumCharacters":0},{"Extension":".png","Name":"favicon-32x32.png","Path":"data/repositories/331450643/static/favicon-32x32.png","Language":".png","Category":"Asset","LOC":0,"NumCharacters":0},{"Extension":".ico","Name":"favicon.ico","Path":"data/repositories/331450643/static/favicon.ico","Language":".ico","Category":"Asset","LOC":0,"NumCharacters":0},{"Extension":".txt","Name":"robots.txt","Path":"data/repositories/331450643/static/robots.txt","Language":"Plain Text","Category":"Data","LOC":0,"NumCharacters":0},{"Extension":".svg","Name":"safari-pinned-tab.svg","Path":"data/repositories/331450643/static/safari-pinned-tab.svg","Language":".svg","Category":"Asset","LOC":0,"NumCharacters":0},{"Extension":".js","Name":"svelte.config.js","Path":"data/repositories/331450643/svelte.config.js","Language":"JavaScript","Category":"Source Code","LOC":15,"NumCharacters":283},{"Extension":".cjs","Name":"tailwind.config.cjs","Path":"data/repositories/331450643/tailwind.config.cjs","Language":"JavaScript","Category":"Source Code","LOC":8,"NumCharacters":117}]},"UsedPlatforms":{},"UsedFrameworks":{},"Functions":[],"NumFunctions":0,"Packages":[{"RootPath":"data/repositories/331450643","Name":"lil-hash","Description":"","Dependencies":[],"DevDependencies":["@sveltejs/kit","eslint-config-prettier","eslint-plugin-svelte3","postcss","prettier-plugin-svelte","svelte","cssnano","eslint","prettier","svelte-preprocess","tailwindcss","@sveltejs/adapter-cloudflare-workers","autoprefixer","husky","lint-staged","postcss-load-config"],"FaaSRuntimeDependencies":[],"PublishedToNPM":false,"NumPackages":1,"NumFilesByExtension":null,"LinesOfTextByExtension":null,"NumFaaSHandlers":0,"NumFaaSRuntimeDependencies":0}],"NumPackages":1,"NumPublishedToNPM":0,"Dependencies":[],"DevDependencies":["@sveltejs/kit","eslint-config-prettier","eslint-plugin-svelte3","postcss","prettier-plugin-svelte","svelte","cssnano","eslint","prettier","svelte-preprocess","tailwindcss","@sveltejs/adapter-cloudflare-workers","autoprefixer","husky","lint-staged","postcss-load-config"],"FaaSRuntimeDependencies":[],"NumFaaSRuntimeDependencies":0,"NumFaaSHandlers":0}